txt2phrases/__init__.py
txt2phrases/classify_specific.py
txt2phrases/cli.py
txt2phrases/html2txt.py
txt2phrases/keyword.py
txt2phrases/pdf2txt.py
txt2phrases/pygetpaper.py
txt2phrases-1.0.3.dist-info/METADATA
txt2phrases-1.0.3.dist-info/WHEEL
txt2phrases-1.0.3.dist-info/entry_points.txt
txt2phrases-1.0.3.dist-info/top_level.txt
txt2phrases-1.0.3.dist-info/RECORD
