Metadata-Version: 2.4
Name: txt2phrases
Version: 1.0.3
Summary: A comprehensive library for text processing, keyword extraction, and classification from PDF and HTML documents
Home-page: https://github.com/semanticClimate/encyclopedia/tree/main/txt2phrases
Author: Udita Agarwal
Author-email: udita20agarwal@gmail.com
Keywords: text-processing,keyword-extraction,pdf,html,nlp,tf-idf,classification
Classifier: Development Status :: 4 - Beta
Classifier: Intended Audience :: Science/Research
Classifier: Intended Audience :: Developers
Classifier: License :: OSI Approved :: MIT License
Classifier: Operating System :: OS Independent
Classifier: Programming Language :: Python :: 3
Classifier: Programming Language :: Python :: 3.7
Classifier: Programming Language :: Python :: 3.8
Classifier: Programming Language :: Python :: 3.9
Classifier: Programming Language :: Python :: 3.10
Classifier: Programming Language :: Python :: 3.11
Classifier: Topic :: Text Processing
Classifier: Topic :: Scientific/Engineering :: Information Analysis
Classifier: Topic :: Software Development :: Libraries :: Python Modules
Requires-Python: >=3.7
Requires-Dist: beautifulsoup4>=4.9.0
Requires-Dist: transformers>=4.0.0
Requires-Dist: pandas>=1.0.0
Requires-Dist: tqdm>=4.50.0
Requires-Dist: PyPDF2>=2.0.0
Requires-Dist: scikit-learn>=1.0.0
Dynamic: author
Dynamic: author-email
Dynamic: classifier
Dynamic: description
Dynamic: description-content-type
Dynamic: home-page
Dynamic: keywords
Dynamic: requires-dist
Dynamic: requires-python
Dynamic: summary
